lol_bayes_auth/__init__.py
lol_bayes_auth/auth.py
lol_bayes_auth-0.1.4.dist-info/LICENSE
lol_bayes_auth-0.1.4.dist-info/METADATA
lol_bayes_auth-0.1.4.dist-info/WHEEL
lol_bayes_auth-0.1.4.dist-info/RECORD
