Metadata-Version: 2.1
Name: lol_bayes_auth
Version: 0.1.4
Summary: Simple authentication package for the Bayes Esports API
License: GPL-3.0
Author: Allan Cao
Author-email: allan@allancao.ca
Requires-Python: >=3.10,<4.0
Classifier: License :: OSI Approved :: GNU General Public License v3 (GPLv3)
Classifier: Programming Language :: Python :: 3
Classifier: Programming Language :: Python :: 3.10
Classifier: Programming Language :: Python :: 3.11
Classifier: Programming Language :: Python :: 3.12
Requires-Dist: requests (>=2.31.0,<3.0.0)
